deadbatteries/__init__.py
deadbatteries-0.0.1.dist-info/DESCRIPTION.rst
deadbatteries-0.0.1.dist-info/METADATA
deadbatteries-0.0.1.dist-info/RECORD
deadbatteries-0.0.1.dist-info/WHEEL
deadbatteries-0.0.1.dist-info/metadata.json
deadbatteries-0.0.1.dist-info/top_level.txt
